ttsforge/__init__.py
ttsforge/_version.py
ttsforge/audio_merge.py
ttsforge/audio_player.py
ttsforge/chapter_selection.py
ttsforge/constants.py
ttsforge/conversion.py
ttsforge/input_reader.py
ttsforge/kokoro_lang.py
ttsforge/kokoro_runner.py
ttsforge/name_extractor.py
ttsforge/phoneme_conversion.py
ttsforge/phonemes.py
ttsforge/ssmd_generator.py
ttsforge/utils.py
ttsforge/cli/__init__.py
ttsforge/cli/commands_conversion.py
ttsforge/cli/commands_phonemes.py
ttsforge/cli/commands_utility.py
ttsforge/cli/helpers.py
ttsforge/vocab/__init__.py
ttsforge-0.1.1.dist-info/licenses/LICENSE
ttsforge-0.1.1.dist-info/METADATA
ttsforge-0.1.1.dist-info/WHEEL
ttsforge-0.1.1.dist-info/entry_points.txt
ttsforge-0.1.1.dist-info/top_level.txt
ttsforge-0.1.1.dist-info/RECORD
