Metadata-Version: 2.4
Name: ttsforge
Version: 0.1.1
Summary: Generate audiobooks from EPUB files using Kokoro ONNX TTS.
Author-email: Holger Nahrstaedt <nahrstaedt@gmail.com>
License: MIT License
Project-URL: Homepage, https://github.com/holgern/ttsforge
Classifier: Intended Audience :: End Users/Desktop
Classifier: Intended Audience :: Developers
Classifier: License :: OSI Approved :: MIT License
Classifier: Operating System :: OS Independent
Classifier: Programming Language :: Python :: 3
Classifier: Programming Language :: Python :: 3.10
Classifier: Programming Language :: Python :: 3.11
Classifier: Programming Language :: Python :: 3.12
Classifier: Programming Language :: Python :: 3.13
Classifier: Topic :: Multimedia :: Sound/Audio :: Speech
Classifier: Topic :: Software Development :: Libraries
Requires-Python: >=3.10
License-File: LICENSE
Requires-Dist: click>=8.0.0
Requires-Dist: rich>=13.0.0
Requires-Dist: epub2text
Requires-Dist: numpy
Requires-Dist: soundfile>=0.12.0
Requires-Dist: chardet
Requires-Dist: charset-normalizer
Requires-Dist: platformdirs>=3.0.0
Requires-Dist: pykokoro>=0.6.4
Provides-Extra: audio
Requires-Dist: sounddevice>=0.4.6; extra == "audio"
Provides-Extra: dev
Requires-Dist: pytest>=7.0.0; extra == "dev"
Requires-Dist: ruff>=0.1.0; extra == "dev"
Requires-Dist: mypy>=1.8.0; extra == "dev"
Provides-Extra: static-ffmpeg
Requires-Dist: static-ffmpeg>=3.0; extra == "static-ffmpeg"
Provides-Extra: gpu
Requires-Dist: onnxruntime-gpu>=1.16.0; extra == "gpu"
Dynamic: license-file
